class Main$B extends Main$A {
  public Main$B();
    Code:
       0: aload_0       
       1: aconst_null   
       2: invokespecial #1                  // Method Main$A."<init>":(LMain$1;)V
       5: aload_0       
       6: invokestatic  #2                  // Method Main$A.access$100:(LMain$A;)V
       9: getstatic     #3                  // Field java/lang/System.out:Ljava/io/PrintStream;
      12: aload_0       
      13: invokestatic  #4                  // Method Main$A.access$200:(LMain$A;)I
      16: invokevirtual #5                  // Method java/io/PrintStream.println:(I)V
      19: return        
}