private static int lambda$bar$3(int);
  descriptor: (I)I
  flags: ACC_PRIVATE, ACC_STATIC, ACC_SYNTHETIC
  Code:
    stack=1, locals=1, args_size=1
       0: iload_0
       1: ireturn
    LineNumberTable:
      line 32: 0
    LocalVariableTable:
      Start  Length  Slot  Name   Signature
          0       2     0   len   I

private static int lambda$bar$2(java.lang.Object);
  descriptor: (Ljava/lang/Object;)I
  flags: ACC_PRIVATE, ACC_STATIC, ACC_SYNTHETIC
  Code:
    stack=1, locals=1, args_size=1
       0: aload_0
       1: invokevirtual #3                  // Method java/lang/Object.hashCode:()I
       4: ireturn
    LineNumberTable:
      line 29: 0
    LocalVariableTable:
      Start  Length  Slot  Name   Signature
          0       5     0     o   Ljava/lang/Object;

private static int lambda$foo$1(int);
  descriptor: (I)I
  flags: ACC_PRIVATE, ACC_STATIC, ACC_SYNTHETIC
  Code:
    stack=1, locals=1, args_size=1
       0: iload_0
       1: ireturn
    LineNumberTable:
      line 23: 0
    LocalVariableTable:
      Start  Length  Slot  Name   Signature
          0       2     0     h   I

private static int lambda$foo$0();
  descriptor: ()I
  flags: ACC_PRIVATE, ACC_STATIC, ACC_SYNTHETIC
  Code:
    stack=1, locals=0, args_size=0
       0: iconst_0
       1: ireturn
    LineNumberTable:
      line 20: 0