Compiled from "A.java"
public class A {
  private java.lang.String B;

  private int AA;

  public int C;

  public A();
    Code:
       0: aload_0       
       1: invokespecial #1        // Method java/lang/Object."<init>":()V
       4: aload_0       
       5: ldc           #2        // String test_string
       7: putfield      #3        // Field B:Ljava/lang/String;
      10: return        

  private int method1();
    Code:
       0: iconst_0      
       1: istore_1      
       2: iload_1       
       3: ireturn       

  private int method1(int, java.lang.String);
    Code:
       0: iload_1       
       1: istore_3      
       2: iload_3       
       3: ireturn       
}