a.TestNested$A(a.TestNested);
    Code:
       0: aload_0       
       1: aload_1       
       2: putfield      #2                  // Field this$0:La/TestNested;
       5: aload_0       
       6: invokespecial #3                  // Method java/lang/Object."<init>":()V
       9: return        

  private a.TestNested$A(a.TestNested, int);
    Code:
       0: aload_0       
       1: aload_1       
       2: putfield      #2                  // Field this$0:La/TestNested;
       5: aload_0       
       6: invokespecial #3                  // Method java/lang/Object."<init>":()V
       9: return        

  a.TestNested$A(a.TestNested, int, a.TestNested$1);
    Code:
       0: aload_0       
       1: aload_1       
       2: iload_2       
       3: invokespecial #1                  // Method "<init>":(La/TestNested;I)V
       6: return        
}