Compiled from "Test.java"
public class Test {
  public Test();
    Code:
       0: aload_0       
       1: invokespecial #1                  // Method java/lang/Object."<init>":()V
       4: return        

  public static void main(java.lang.String[]);
    Code:
       0: lconst_0      
       1: invokestatic  #2                  // Method java/lang/Long.valueOf:(J)Ljava/lang/Long;
       4: astore_1      
       5: lconst_0      
       6: invokestatic  #2                  // Method java/lang/Long.valueOf:(J)Ljava/lang/Long;
       9: astore_2      
      10: return        
}