0: new           #2                  // class java/lang/String
   3: dup           
   4: ldc           #3                  // String Android
   6: invokespecial #4                  // Method java/lang/String."<init>":(Ljava/lang/String;)V
   9: astore_1      
  10: aload_1       
  11: invokevirtual #5                  // Method java/lang/String.intern:()Ljava/lang/String;
  14: astore_1      
  15: new           #2                  // class java/lang/String
  18: dup           
  19: ldc           #6                  // String java
  21: invokespecial #4                  // Method java/lang/String."<init>":(Ljava/lang/String;)V
  24: astore_2      
  25: aload_2       
  26: invokevirtual #5                  // Method java/lang/String.intern:()Ljava/lang/String;
  29: astore_2      
  30: return