Compiled from "Test1.java"
public class Test1 {
  public Test1();
    Code:
       0: aload_0       
       1: invokespecial #10                 // Method java/lang/Object."<init>":()V
       4: aload_0       
       5: new           #12                 // class java/util/Scanner
       8: dup           
       9: getstatic     #14                 // Field java/lang/System.in:Ljava/io/InputStream;
      12: invokespecial #19                 // Method java/util/Scanner."<init>":(Ljava/io/InputStream;)V
      15: putfield      #22                 // Field in:Ljava/util/Scanner;
      18: return        
}