Compiled from "ImplicitTest.java"
public class ImplicitTest extends java.lang.Object{
public ImplicitTest();
  Code:
   0:   aload_0
   1:   invokespecial   #1; //Method java/lang/Object."<init>":()V
   4:   return

public static void main(java.lang.String[]);
  Code:
   0:   iconst_1
   1:   invokestatic    #2; //Method java/lang/Boolean.valueOf:(Z)Ljava/lang/Boolean;
   4:   astore_1
   5:   aload_1
   6:   invokevirtual   #3; //Method java/lang/Boolean.booleanValue:()Z
   9:   istore_2
   10:  aload_1
   11:  invokevirtual   #3; //Method java/lang/Boolean.booleanValue:()Z
   14:  istore_3
   15:  return

}