class Main$1LocalClass {
  final int val$y;

  final Main this$0;

  Main$1LocalClass();
    Code:
       0: aload_0
       1: aload_1
       2: putfield      #1                  // Field this$0:LMain;
       5: aload_0
       6: iload_2
       7: putfield      #2                  // Field val$y:I
      10: aload_0
      11: invokespecial #3                  // Method java/lang/Object."<init>":()V
      14: getstatic     #4                  // Field java/lang/System.out:Ljava/io/PrintStream;
      17: aload_0
      18: getfield      #2                  // Field val$y:I
      21: invokevirtual #5                  // Method java/io/PrintStream.println:(I)V
      24: return
}