Compiled from "Main.java"
public class com.severityone.test.Main {
  public com.severityone.test.Main();
    Code:
       0: aload_0
       1: invokespecial #1                  // Method java/lang/Object."<init>":()V
       4: return

  public static void main(java.lang.String[]);
    Code:
       0: iconst_0
       1: istore_1
       2: getstatic     #2                  // Field java/lang/Boolean.FALSE:Ljava/lang/Boolean;
       5: iconst_0
       6: invokestatic  #3                  // Method java/lang/Boolean.valueOf:(Z)Ljava/lang/Boolean;
       9: invokevirtual #4                  // Method java/lang/Boolean.equals:(Ljava/lang/Object;)Z
      12: istore_2
      13: iconst_1
      14: istore_3
      15: iconst_1
      16: istore        4
      18: return
}