class Test {
  private java.lang.String s;

  Test();
    Code:
       0: aload_0
       1: invokespecial #10                 // Method java/lang/Object."<init>":()V
       4: aload_0
       5: ldc           #12                 // String TESTTEST
       7: putfield      #14                 // Field s:Ljava/lang/String;
      10: return

  Test(int);
    Code:
       0: aload_0
       1: invokespecial #10                 // Method java/lang/Object."<init>":()V
       4: aload_0
       5: ldc           #12                 // String TESTTEST
       7: putfield      #14                 // Field s:Ljava/lang/String;
      10: return
}