public static void main(java.lang.String[]);
Code:
   0: new           #2                  // class Foo
   3: dup           
   4: new           #2                  // class Foo
   7: dup           
   8: new           #2                  // class Foo
  11: dup           
  12: new           #2                  // class Foo
  15: dup           
  16: aconst_null   
  17: invokespecial #3                  // Method "<init>":(LFoo;)V
  20: invokespecial #3                  // Method "<init>":(LFoo;)V
  23: invokespecial #3                  // Method "<init>":(LFoo;)V
  26: invokespecial #3                  // Method "<init>":(LFoo;)V
  29: pop           
  30: return