public class ReturnDouble {
  public ReturnDouble();
    Code:
       0: aload_0
       1: invokespecial #1                  // Method java/lang/Object."<init>":()V
       4: return

  static double returnF();
    Code:
       0: dconst_0
       1: dreturn

  static double returnD();
    Code:
       0: dconst_0
       1: dreturn

  static double returnI();
    Code:
       0: dconst_0
       1: dreturn

  static double returnL();
    Code:
       0: dconst_0
       1: dreturn

  static double returnS();
    Code:
       0: dconst_0
       1: dreturn

  static double returnC();
    Code:
       0: dconst_0
       1: dreturn
}