0: new #2; //class java/lang/Integer
3: dup
4: iconst_3
5: invokespecial #3; //Method java/lang/Integer."<init>":(I)V
8: astore_1
9: aload_1
10: astore_2
11: iconst_4
12: anewarray #2; //class java/lang/Integer
15: dup
16: iconst_0
17: iconst_1
18: invokestatic #4; //Method java/lang/Integer.valueOf:(I)Ljava/lang/Integer;
21: aastore
...
90: iconst_3
91: istore 6
93: iload 6
95: invokestatic #4; //Method java/lang/Integer.valueOf:(I)Ljava/lang/Integer;
98: astore 7
100: iconst_4
101: anewarray #2; //class java/lang/Integer
104: dup
105: iconst_0
106: iconst_1
107: invokestatic #4; //Method java/lang/Integer.valueOf:(I)Ljava/lang/Integer;
110: aastore
111: dup
...