static {};
  Code:
   0:   new #13; //class tools/PieceColor$1
   3:   dup
   4:   ldc #15; //String Black
   6:   iconst_0
   7:   invokespecial   #16; //Method tools/PieceColor$1."<init>":(Ljava/lang/String;I)V
   10:  putstatic   #20; //Field Black:Ltools/PieceColor;
   13:  new #22; //class tools/PieceColor$2
   16:  dup
   17:  ldc #24; //String White
   19:  iconst_1
   20:  invokespecial   #25; //Method tools/PieceColor$2."<init>":(Ljava/lang/String;I)V
   23:  putstatic   #26; //Field White:Ltools/PieceColor;